Metadata-Version: 2.1
Name: createpyproject
Version: 0.0.10
Summary: Test project to use python script for creating barebone python project folder structure
Home-page: https://github.com/srijanss/createpy
Author: Srijan Manandhar
Author-email: srijan.manandhar@gmail.com
License: UNKNOWN
Platform: UNKNOWN
Classifier: Programming Language :: Python :: 3
Classifier: License :: OSI Approved :: MIT License
Classifier: Operating System :: OS Independent
Requires-Python: >=2.7, >=3.0
